gateway/Dockerfile.gateway
gateway/__init__.py
gateway/__main__.py
gateway/docker-compose.local.yml
gateway/serve.py
gateway/validate_config.py
gateway/common/__init__.py
gateway/common/authorization.py
gateway/common/config_manager.py
gateway/common/constants.py
gateway/common/guardrails.py
gateway/common/request_context.py
gateway/converters/__init__.py
gateway/converters/anthropic_to_invariant.py
gateway/converters/gemini_to_invariant.py
gateway/integrations/__init__.py
gateway/integrations/explorer.py
gateway/integrations/guardrails.py
gateway/mcp/__init__.py
gateway/mcp/constants.py
gateway/mcp/log.py
gateway/mcp/mcp_sessions_manager.py
gateway/mcp/mcp_transport_base.py
gateway/mcp/sse.py
gateway/mcp/stdio.py
gateway/mcp/streamable.py
gateway/routes/__init__.py
gateway/routes/anthropic.py
gateway/routes/base_provider.py
gateway/routes/gemini.py
gateway/routes/instrumentation.py
gateway/routes/open_ai.py
invariant_gateway-0.0.9.dist-info/licenses/LICENSE
invariant_gateway-0.0.9.dist-info/METADATA
invariant_gateway-0.0.9.dist-info/WHEEL
invariant_gateway-0.0.9.dist-info/entry_points.txt
invariant_gateway-0.0.9.dist-info/top_level.txt
invariant_gateway-0.0.9.dist-info/RECORD
