Metadata-Version: 2.4
Name: invariant-gateway
Version: 0.0.9
Summary: LLM proxy to observe and debug what your AI agents are doing
Requires-Python: >=3.12
License-File: LICENSE
Requires-Dist: fastapi==0.115.7
Requires-Dist: httpx==0.28.1
Requires-Dist: httpx-sse==0.4.0
Requires-Dist: invariant-sdk>=0.0.11
Requires-Dist: starlette-compress==1.4.0
Requires-Dist: uvicorn==0.34.0
Dynamic: license-file
